gbmgeometry/__init__.py
gbmgeometry/_version.py
gbmgeometry/gbm.py
gbmgeometry/gbm_detector.py
gbmgeometry/gbm_frame.py
gbmgeometry/position_interpolator.py
gbmgeometry/data/balrog.fits
gbmgeometry/data/balrog_trig.fits
gbmgeometry/data/countries.h5
gbmgeometry/data/earth_day.jpg
gbmgeometry/data/earth_midnight.jpg
gbmgeometry/data/earth_night.jpg
gbmgeometry/data/glg_poshist_all_151013_v00.fit
gbmgeometry/data/glg_trigdat_all_bn080916009_v02.fit
gbmgeometry/data/posthist.h5
gbmgeometry/data/thats_no_moon.jpg
gbmgeometry/data/thats_no_moon_big.jpg
gbmgeometry/data/trigdat.h5
gbmgeometry/geometry/__init__.py
gbmgeometry/geometry/cirs_to_gcrs.py
gbmgeometry/geometry/cone.py
gbmgeometry/geometry/cube.py
gbmgeometry/geometry/get_sc_matrix.py
gbmgeometry/geometry/quarternion.py
gbmgeometry/geometry/ray.py
gbmgeometry/geometry/sphere.py
gbmgeometry/geometry/surface.py
gbmgeometry/geometry/volume.py
gbmgeometry/io/__init__.py
gbmgeometry/io/data_download.py
gbmgeometry/spacecraft/__init__.py
gbmgeometry/spacecraft/fermi.py
gbmgeometry/spacecraft/gbm_detectors.py
gbmgeometry/spacecraft/geometry.py
gbmgeometry/spacecraft/lat.py
gbmgeometry/spacecraft/solar_panels.py
gbmgeometry/utils/__init__.py
gbmgeometry/utils/array_to_cmap.py
gbmgeometry/utils/file_converters.py
gbmgeometry/utils/gbm_time.py
gbmgeometry/utils/package_utils.py
gbmgeometry/utils/plotting/__init__.py
gbmgeometry/utils/plotting/angle.py
gbmgeometry/utils/plotting/heavenly_bodies.py
gbmgeometry/utils/plotting/itrs_frame_monkeypatch.py
gbmgeometry/utils/plotting/projections.py
gbmgeometry/utils/plotting/sky_point.py
gbmgeometry/utils/plotting/skyplot.py
gbmgeometry/utils/plotting/space_plot.py
gbmgeometry/utils/plotting/spherical_circle.py
gbmgeometry-0.9.6.data/scripts/get_posthist
gbmgeometry-0.9.6.data/scripts/get_trigdat
gbmgeometry-0.9.6.dist-info/LICENSE
gbmgeometry-0.9.6.dist-info/METADATA
gbmgeometry-0.9.6.dist-info/WHEEL
gbmgeometry-0.9.6.dist-info/top_level.txt
gbmgeometry-0.9.6.dist-info/RECORD
