Metadata-Version: 2.1
Name: gbmgeometry
Version: 0.9.6
Summary: Geometry calculations for Fermi GBM
Home-page: https://github.com/grburgess/gbmgeometry
Author: J. Michael Burgess
Author-email: jmichaelburgess@gmail.com
License: BSD
Project-URL: Bug Tracker, https://github.com/grburgess/gbmgeometry/issues
Project-URL: Source Code, https://github.com/grburgess/gbmgeometry
Platform: UNKNOWN
Requires-Dist: astropy
Requires-Dist: numpy
Requires-Dist: matplotlib
Requires-Dist: sympy
Requires-Dist: healpy
Requires-Dist: spherical-geometry
Requires-Dist: h5py
Requires-Dist: ipyvolume (>=0.6.0a2)
Requires-Dist: numba
